{
    "UserAccess": [
        {
            "Identifiers": ["Anonymous"],
            "Access": {
                "SessionCatalog": true,
                "MyIgnite": false,
                "ScheduleBuilder": false,
                "MobileApp": false,
                "MeetingScheduler": false,
                "MobileAppMessaging": false,
                "LocationBasedMessaging": false
            },
            "VisibleAttendeeTypes": [],
            "Reporting": {
                "SessionCounts": false
            },
            "EvalAccess": [],
            "SessionSetAccess": [{
                    "ApplicableFrom": null,
                    "ApplicableTo": null,
                    "Identifier": "Session Catalog"
                }
            ]
        },
        {
            "Identifiers": [
                "Partner - All Access",
                "MS - All Access"
            ],
            "Access": {
                "SessionCatalog": true,
                "MyIgnite": true,
                "ScheduleBuilder": true,
                "MobileApp": true,
                "MeetingScheduler": true,
                "MobileAppMessaging": true
            },
            "VisibleAttendeeTypes": [
                "Partner - All Access",
                "MS - All Access"
            ],
            "Reporting": {
                "SessionCounts": true
            },
            "EvalAccess": [{
                "Identifier": "PostEventSurvey",
                "SessionTypes": ["Post Event  Survey"],
                "Mobile": true,
                "WebSite": true
            }, {
                "Identifier": "RegularSessionEvaluations",
                "SessionTypes": [
                    "Breakout: 45 minute",
                    "Breakout: 75 minute",
                    "General Session",
                    "Microsoft Studio",
                    "Theater",
                    "Workshop",
                    "MVP PreDay",
                    "Pre-Day Training"
                ],
                "Mobile": true,
                "WebSite": true
            }, {
                "Identifier": "KeynoteAfternoonEvaluation",
                "SessionTypes": ["Technology Keynote"],
                "Mobile": true,
                "WebSite": true
            }, {
                "Identifier": "KeynoteMorningEvaluation",
                "SessionTypes": ["Vision Keynote"],
                "Mobile": true,
                "WebSite": true
            }],
            "SessionSetAccess": [{
                    "ApplicableFrom": null,
                    "ApplicableTo": null,
                    "Identifier": "Schedule Builder - Attendee"
                },
                {
                    "ApplicableFrom": null,
                    "ApplicableTo": null,
                    "Identifier": "Lab"
                },
                {
                    "ApplicableFrom": null,
                    "ApplicableTo": null,
                    "Identifier": "My Schedule - Attendee"
                }
            ]
        }
    ]
}