{
  "UserAccess": [
    {
      "Identifiers": ["Anonymous"],
      "Access": {
        "SessionCatalog": true,
        "MyIgnite": false,
        "ScheduleBuilder": false,
        "MobileApp": false,
        "MeetingScheduler": false,
        "MobileAppMessaging": false,
        "LocationBasedMessaging": false,
        "InPersonExperience": false
      },
      "VisibleAttendeeTypes": [],
      "Reporting": {
        "SessionCounts": false
      },
      "EvalAccess": [],
      "SessionSetAccess": []
    },
    {
      "Identifiers": [
        "Microsoft Attendee",
        "Partner Attendee A",
        "Microsoft Speaker",
        "External Speaker",
        "Crew",
        "Partner Attendee B",
        "Non-Attending User"
      ],
      "Access": {
        "SessionCatalog": true,
        "MyIgnite": true,
        "ScheduleBuilder": true,
        "MobileApp": true,
        "MeetingScheduler": true,
        "MobileAppMessaging": true,
        "LocationBasedMessaging": true,
        "InPersonExperience": true
      },
      "VisibleAttendeeTypes": [
        "Partner Attendee",
        "Sponsor Attendee",
        "Crew",
        "External Speaker",
        "Microsoft Attendee",
        "Microsoft Speaker"
      ],
      "Reporting": {
        "SessionCounts": false
      },
      "EvalAccess": [],
      "SessionSetAccess": [
        {
          "ApplicableFrom": null,
          "ApplicableTo": null,
          "Identifier": "Session Scheduler"
        }
      ]
    }
  ]
}
